fix_conda_ssl/__init__.py
fix_conda_ssl/app.py
fix_conda_ssl/app.tcss
fix_conda_ssl-0.3.2.dist-info/LICENSE
fix_conda_ssl-0.3.2.dist-info/METADATA
fix_conda_ssl-0.3.2.dist-info/WHEEL
fix_conda_ssl-0.3.2.dist-info/entry_points.txt
fix_conda_ssl-0.3.2.dist-info/RECORD
