Metadata-Version: 2.1
Name: fix-conda-ssl
Version: 0.3.2
Summary: Fix Conda SSLError on Windows by copying DDLs
Home-page: https://github.com/davidfokkema/fix-conda-ssl
License: GPL-3.0-or-later
Author: David Fokkema
Author-email: davidfokkema@icloud.com
Requires-Python: >=3.9,<4.0
Classifier: Development Status :: 4 - Beta
Classifier: Environment :: Console
Classifier: License :: OSI Approved :: GNU General Public License v3 or later (GPLv3+)
Classifier: Operating System :: Microsoft :: Windows
Classifier: Programming Language :: Python :: 3
Classifier: Programming Language :: Python :: 3.9
Classifier: Programming Language :: Python :: 3.10
Classifier: Programming Language :: Python :: 3.11
Classifier: Programming Language :: Python :: 3.12
Requires-Dist: textual (>=0.41.0,<0.42.0)
